[{"taskName":"newtask","taskId":"b03de203-459c-422c-a02c-2f93d252b882","tags":[],"percentComplete":25,"tasks":[],"lastUpdated":"February 18th 2019, 10:46:44 pm","hours":0,"hoursLog":[],"notes":[],"textEditorContent":"Go ahead, write some notes"},{"taskName":"new","taskId":"768d814c-1e61-4deb-893c-a5f5e94987fe","tags":[],"percentComplete":25,"tasks":[],"lastUpdated":"February 18th 2019, 10:47:03 pm","hours":0,"hoursLog":[],"notes":[],"textEditorContent":"Go ahead, write some notes"},{"taskName":"new2","taskId":"c7d05b55-76f5-4438-97fc-60ff185fc26f","tags":[],"percentComplete":25,"tasks":[],"lastUpdated":"February 18th 2019, 10:47:05 pm","hours":0,"hoursLog":[],"notes":[],"textEditorContent":"Go ahead, write some notes"}]