[{"taskName":"firstTask","taskId":"63741eb3-9c2a-461d-9b61-bf1f35562d2b","tags":["testingCreateNewTag","testingCreateNewTag","testingCreateNewTag","testingCreateNewTagAgain","testingCreateNewTagAgain","testingCreateNewTagAgain","testingCreateNewTagAgain","testingCreateNewTagAgain",null,null,"tagInputtestsgtg","tagInputa","tagInput","tagInputgagtg","tagInputtgsdt","tagInputhhchx","testingtesting","arar","","","","","","","","","","","fa","fa","fa","fa","fa","fa","fa","fa","fa","fa","fa","fa","fa","fa","fa","fa","","","gsfg","hey there","ydhy","","hey","testing now","yes","testing"],"percentComplete":25,"tasks":[{"text":"testingtesting","active":true,"id":"57ddfe98-78e4-4b2d-a640-2bb5df917382"}],"lastUpdated":"2019-03-03T22:30:20.852Z","hours":0,"hoursLog":[{"taskName":"firstTask","tags":["agarg"],"startTime":"2019-03-09T09:52:12.880Z","stopTime":"2019-03-09T09:52:14.113Z"},{"taskName":"firstTask","tags":[],"startTime":"2019-03-09T09:52:15.080Z","stopTime":"2019-03-09T09:52:17.500Z"},{"taskName":"firstTask","tags":[],"startTime":"2019-03-10T01:13:53.716Z","stopTime":"2019-03-10T01:13:56.369Z"},{"taskName":"firstTask","tags":[],"startTime":"2019-03-10T01:14:03.538Z","stopTime":"2019-03-10T01:14:04.123Z"}],"notes":[],"textEditorContent":"Go ahead, write some notes"},{"taskName":"coding","taskId":"a010378a-7d47-40f5-bc07-c5e93935b67f","tags":["","","","","","","","","","","hello","test","testing again","test"],"percentComplete":25,"tasks":[],"lastUpdated":"2019-03-04T19:48:46.366Z","hours":0,"hoursLog":[{"taskName":"coding","tags":["there","es","test"],"startTime":"2019-03-09T07:31:28.472Z","stopTime":"2019-03-09T07:31:32.585Z"},{"taskName":"coding","tags":[],"startTime":"2019-03-09T08:20:20.470Z","stopTime":"2019-03-09T08:20:23.480Z"}],"notes":[],"textEditorContent":"Go ahead, write some notes"},{"taskName":"thirdTask","taskId":"9f54b845-b521-41ad-ba1b-4b2690f0fbb4","tags":["farf"],"percentComplete":25,"tasks":[],"lastUpdated":"2019-03-04T22:51:54.211Z","hours":0,"hoursLog":[],"notes":[],"textEditorContent":"Go ahead, write some notes"},{"taskName":"third task","taskId":"48c93109-3baf-4ef1-8ca6-23500950a677","tags":["","","","","","","","","","","","","","","","hh",""],"percentComplete":25,"tasks":[],"lastUpdated":"2019-03-07T03:16:27.134Z","hours":0,"hoursLog":[{"taskName":"third task","startTime":"2019-03-07T07:20:15.977Z","stopTime":"2019-03-07T07:20:21.821Z","tags":["hey"]},{"taskName":"third task","tags":[],"startTime":"2019-03-08T08:09:01.891Z","stopTime":"2019-03-08T08:09:02.924Z"}],"notes":[],"textEditorContent":"Go ahead, write some notes"},{"taskName":"4thtask","taskId":"d7a1ed61-ee07-4a3f-a0a9-1a740f712ea6","tags":[],"percentComplete":25,"tasks":[],"lastUpdated":"2019-03-08T08:09:13.547Z","hours":0,"hoursLog":[{"taskName":"4thtask","tags":[],"startTime":"2019-03-08T08:09:12.088Z","stopTime":"2019-03-08T08:09:13.542Z"}],"notes":[],"textEditorContent":"Go ahead, write some notes"},{"taskName":"testagain","taskId":"3ec41650-3ca9-4d99-9623-207bb6608337","tags":[],"percentComplete":25,"tasks":[],"lastUpdated":"2019-03-09T07:19:29.654Z","hours":0,"hoursLog":[{"taskName":"testagain","tags":[],"startTime":"2019-03-09T07:19:31.242Z","stopTime":"2019-03-09T07:19:32.859Z"}],"notes":[],"textEditorContent":"Go ahead, write some notes"},{"taskName":"testAgain","taskId":"05b6dfb0-ac76-45e4-a163-0e5d249abcd3","tags":[],"percentComplete":25,"tasks":[],"lastUpdated":"2019-03-09T09:54:07.435Z","hours":0,"hoursLog":[{"taskName":"testAgain","tags":[],"startTime":"2019-03-09T09:58:03.703Z","stopTime":"2019-03-09T09:58:05.164Z"},{"taskName":"testAgain","tags":[],"startTime":"2019-03-09T10:09:19.831Z","stopTime":"2019-03-09T10:09:23.290Z"},{"taskName":"testAgain","tags":[],"startTime":"2019-03-09T11:51:35.190Z","stopTime":"2019-03-09T11:51:38.536Z"},{"taskName":"testAgain","tags":[],"startTime":"2019-03-09T11:51:39.859Z","stopTime":"2019-03-09T11:51:41.085Z"}],"notes":[],"textEditorContent":"Go ahead, write some notes"}]